lzlzhn/Call_A_Roll.py
lzlzhn/QR.py
lzlzhn/__init__.py
lzlzhn/author.py
lzlzhn/guide.py
lzlzhn/message.py
lzlzhn/name.py
lzlzhn/points.py
lzlzhn/points_tester.py
lzlzhn-2022.11.16.1823.3.dist-info/METADATA
lzlzhn-2022.11.16.1823.3.dist-info/WHEEL
lzlzhn-2022.11.16.1823.3.dist-info/top_level.txt
lzlzhn-2022.11.16.1823.3.dist-info/RECORD
